README
setup.py
src/fiveruns/__init__.py
src/fiveruns.dash.egg-info/PKG-INFO
src/fiveruns.dash.egg-info/SOURCES.txt
src/fiveruns.dash.egg-info/dependency_links.txt
src/fiveruns.dash.egg-info/namespace_packages.txt
src/fiveruns.dash.egg-info/requires.txt
src/fiveruns.dash.egg-info/top_level.txt
src/fiveruns/dash/__init__.py
src/fiveruns/dash/configuration.py
src/fiveruns/dash/exceptions.py
src/fiveruns/dash/metrics.py
src/fiveruns/dash/protocol.py
src/fiveruns/dash/recipes.py
src/fiveruns/dash/session.py
src/fiveruns/dash/version.py
src/fiveruns/dash/scm/__init__.py
src/fiveruns/dash/scm/handler.py
src/fiveruns/dash/scm/handlers/__init__.py
src/fiveruns/dash/scm/handlers/_git.py
src/fiveruns/dash/scm/handlers/_svn.py
src/fiveruns/recipes/__init__.py
src/fiveruns/recipes/python.py
src/fiveruns/tests/__init__.py
src/fiveruns/tests/configuration.py
src/fiveruns/tests/exceptions.py
src/fiveruns/tests/helper.py
src/fiveruns/tests/metrics.py
src/fiveruns/tests/protocol.py
src/fiveruns/tests/recipe.py
src/fiveruns/tests/session.py
src/fiveruns/tests/tests.py