Metadata-Version: 1.0
Name: fiveruns.dash
Version: 0.4
Summary: FiveRuns Dash base library for Python
Home-page: http://dash.fiveruns.com
Author: FiveRuns Development Team
Author-email: dev@fiveruns.com
License: MIT
Keywords: monitoring performance production metrics logging
Platform: UNKNOWN
